btgitserver/__init__.py
btgitserver/app.py
btgitserver/args.py
btgitserver/config.py
btgitserver/defaults.py
btgitserver/logger.py
btgitserver-3.2.0.data/data/bin/etc/config.yaml
btgitserver-3.2.0.dist-info/METADATA
btgitserver-3.2.0.dist-info/WHEEL
btgitserver-3.2.0.dist-info/entry_points.txt
btgitserver-3.2.0.dist-info/top_level.txt
btgitserver-3.2.0.dist-info/RECORD
