Metadata-Version: 2.4
Name: btgitserver
Version: 3.2.0
Summary: Python-based Git Server
Home-page: https://github.com/berttejeda/bert.git-server
Author: Engelbert Tejeda
Author-email: berttejeda@gmail.com
Keywords: yaml,configuration,config,file,python,settings
Classifier: Development Status :: 3 - Alpha
Classifier: Intended Audience :: Developers
Classifier: Intended Audience :: Information Technology
Classifier: License :: OSI Approved :: MIT License
Classifier: Natural Language :: English
Classifier: Programming Language :: Python :: 3.7
Requires-Python: >=3.7
Requires-Dist: btconfig<5.0.0,>=4.4.4
Requires-Dist: coloredlogs<16.0,>=15.0.0
Requires-Dist: setuptools
Requires-Dist: dulwich<1.0,>=0.22.1
Requires-Dist: flask<4.0.0,>=3.0.3
Requires-Dist: Flask-HTTPAuth<5.0.0,>=4.8.0
Requires-Dist: gunicorn<21.0.0,>=20.1.0
Provides-Extra: tests
Requires-Dist: pytest; extra == "tests"
Requires-Dist: pytest-cov; extra == "tests"
Requires-Dist: coveralls; extra == "tests"
Requires-Dist: flake8; extra == "tests"
Requires-Dist: mypy; extra == "tests"
